segment_config_api/__init__.py
segment_config_api/api.py
segment_config_api/models/__init__.py
segment_config_api/models/base_model.py
segment_config_api/models/deletion_and_suppression.py
segment_config_api/models/destination_filters.py
segment_config_api/models/destinations.py
segment_config_api/models/event_delivery_metrics.py
segment_config_api/models/iam.py
segment_config_api/models/integrations_catalog.py
segment_config_api/models/sources.py
segment_config_api/models/tracking_plans.py
segment_config_api/models/workspaces.py
segment_config_api-0.0.1.dist-info/METADATA
segment_config_api-0.0.1.dist-info/WHEEL
segment_config_api-0.0.1.dist-info/top_level.txt
segment_config_api-0.0.1.dist-info/RECORD
